[
        {
                "id": "1",
                "c1": "Productos para mascotas y animales"
        },
        {
                "id": "166",
                "c1": "Ropa y accesorios"
        },
        {
                "id": "222",
                "c1": "Electrónica"
        },
        {
                "id": "469",
                "c1": "Salud y belleza"
        },
        {
                "id": "1239",
                "c1": "Juegos y juguetes"
        },
        {
                "id": "536",
                "c1": "Casa y jardín"
        },
        {
                "id": "412",
                "c1": "Alimentación, bebida y tabaco"
        },
        {
                "id": "922",
                "c1": "Material de oficina"
        },
        {
                "id": "783",
                "c1": "Multimedia"
        }
]